trophyweb/__init__.py
trophyweb/static/applause4.wav
trophyweb/static/curtains.png
trophyweb/static/env_grad.png
trophyweb/static/env_white.png
trophyweb/static/index.html
trophyweb/static/main.css
trophyweb/static/main.js
trophyweb/static/minotti_1.jpg
trophyweb/static/trophy_minimal.glb
trophyweb-0.0.1.dist-info/METADATA
trophyweb-0.0.1.dist-info/RECORD
trophyweb-0.0.1.dist-info/WHEEL
trophyweb-0.0.1.dist-info/top_level.txt
