Metadata-Version: 2.1
Name: trophyweb
Version: 0.0.1
Summary: Trophy Case App for All-Inspiration
Home-page: https://github.com/frugs/allin-web
Author: Hugo Wainwright
Author-email: wainwrighthugo@gmail.com
License: UNKNOWN
Keywords: sc2,trophy
Platform: UNKNOWN
Requires-Dist: flask
